general/__init__.py
general/file_tool.py
BinResearchTools-0.0.1.dist-info/LICENCE
BinResearchTools-0.0.1.dist-info/METADATA
BinResearchTools-0.0.1.dist-info/WHEEL
BinResearchTools-0.0.1.dist-info/top_level.txt
BinResearchTools-0.0.1.dist-info/RECORD
